scake/__init__.py
scake/scake.py
scake/libcore/__init__.py
scake/libcore/config_loader.py
scake/libcore/sck_format.py
scake/libcore/sck_graph.py
scake/libcore/sck_log.py
scake/libcore/sck_singleton.py
scake-0.3.3.dist-info/LICENSE
scake-0.3.3.dist-info/METADATA
scake-0.3.3.dist-info/WHEEL
scake-0.3.3.dist-info/top_level.txt
scake-0.3.3.dist-info/RECORD
